memgpt/__init__.py
memgpt/__main__.py
memgpt/agent.py
memgpt/agent_store/chroma.py
memgpt/agent_store/db.py
memgpt/agent_store/lancedb.py
memgpt/agent_store/milvus.py
memgpt/agent_store/qdrant.py
memgpt/agent_store/storage.py
memgpt/autogen/README.md
memgpt/autogen/__init__.py
memgpt/autogen/examples/agent_autoreply.py
memgpt/autogen/examples/agent_docs.py
memgpt/autogen/examples/agent_groupchat.py
memgpt/autogen/examples/memgpt_coder_autogen.ipynb
memgpt/autogen/interface.py
memgpt/autogen/memgpt_agent.py
memgpt/benchmark/benchmark.py
memgpt/benchmark/constants.py
memgpt/cli/cli.py
memgpt/cli/cli_config.py
memgpt/cli/cli_load.py
memgpt/client/__init__.py
memgpt/client/admin.py
memgpt/client/client.py
memgpt/client/streaming.py
memgpt/client/utils.py
memgpt/config.py
memgpt/configs/anthropic.json
memgpt/configs/memgpt_hosted.json
memgpt/configs/openai.json
memgpt/constants.py
memgpt/credentials.py
memgpt/data_sources/connectors.py
memgpt/embeddings.py
memgpt/errors.py
memgpt/functions/__init__.py
memgpt/functions/function_sets/base.py
memgpt/functions/function_sets/extras.py
memgpt/functions/functions.py
memgpt/functions/schema_generator.py
memgpt/humans/__init__.py
memgpt/humans/examples/basic.txt
memgpt/humans/examples/cs_phd.txt
memgpt/interface.py
memgpt/llm_api/__init__.py
memgpt/llm_api/anthropic.py
memgpt/llm_api/azure_openai.py
memgpt/llm_api/cohere.py
memgpt/llm_api/google_ai.py
memgpt/llm_api/llm_api_tools.py
memgpt/llm_api/openai.py
memgpt/local_llm/README.md
memgpt/local_llm/__init__.py
memgpt/local_llm/chat_completion_proxy.py
memgpt/local_llm/constants.py
memgpt/local_llm/function_parser.py
memgpt/local_llm/grammars/__init__.py
memgpt/local_llm/grammars/gbnf_grammar_generator.py
memgpt/local_llm/grammars/json.gbnf
memgpt/local_llm/grammars/json_func_calls_with_inner_thoughts.gbnf
memgpt/local_llm/groq/api.py
memgpt/local_llm/json_parser.py
memgpt/local_llm/koboldcpp/api.py
memgpt/local_llm/koboldcpp/settings.py
memgpt/local_llm/llamacpp/api.py
pymemgpt_nightly-0.4.0.dev20240923104140.dist-info/LICENSE
pymemgpt_nightly-0.4.0.dev20240923104140.dist-info/METADATA
pymemgpt_nightly-0.4.0.dev20240923104140.dist-info/WHEEL
pymemgpt_nightly-0.4.0.dev20240923104140.dist-info/entry_points.txt
pymemgpt_nightly-0.4.0.dev20240923104140.dist-info/RECORD
